sophisthse/__init__.py
sophisthse/constants.py
sophisthse/sophisthse.py
sophisthse/cache/.gitkeep
sophisthse-0.1.1.dist-info/WHEEL
sophisthse-0.1.1.dist-info/METADATA
sophisthse-0.1.1.dist-info/RECORD
