Metadata-Version: 2.1
Name: sophisthse
Version: 0.1.1
Summary: SophistHSE package provides methods to access timeseries data from sophist.hse.ru using Python.
Author-email: Aleksei Prishchepo <sophisthse@outlook.com>
Requires-Python: >=3.8
Classifier: Programming Language :: Python :: 3
Classifier: License :: OSI Approved :: MIT License
Classifier: Operating System :: OS Independent
Classifier: Development Status :: 2 - Pre-Alpha
Classifier: Topic :: Scientific/Engineering :: Information Analysis
Classifier: Topic :: Software Development :: Libraries :: Python Modules
Classifier: Intended Audience :: Science/Research
Requires-Dist: beautifulsoup4
Requires-Dist: html5lib
Requires-Dist: lxml
Requires-Dist: pandas
Requires-Dist: Requests
Requires-Dist: pytest ; extra == "dev"
Requires-Dist: pytest-cov ; extra == "dev"
Requires-Dist: requests_mock ; extra == "dev"
Requires-Dist: flake8 ; extra == "dev"
Requires-Dist: black ; extra == "dev"
Project-URL: Homepage, https://github.com/AlekseiPrishchepo/pysophisthse
Project-URL: Source, https://github.com/AlekseiPrishchepo/pysophisthse
Provides-Extra: dev
